AOF_Ske_Pkg/__init__.py
AOF_Ske_Pkg/compute_2D_aof.py
AOF_Ske_Pkg/distance_transform.py
AOF_Ske_Pkg/medial_axis.py
AOF_Ske_Pkg/utils.py
aof_testinh_ske-0.0.4.dist-info/LICENSE
aof_testinh_ske-0.0.4.dist-info/METADATA
aof_testinh_ske-0.0.4.dist-info/WHEEL
aof_testinh_ske-0.0.4.dist-info/top_level.txt
aof_testinh_ske-0.0.4.dist-info/RECORD
