Metadata-Version: 2.1
Name: aof-testinh-ske
Version: 0.0.4
Summary: test_pkg_aof_ske
Home-page: UNKNOWN
Author: testing
Author-email: 
License: UNKNOWN
Keywords: python
Platform: UNKNOWN
Classifier: Development Status :: 1 - Planning
Classifier: Intended Audience :: Developers
Classifier: Programming Language :: Python :: 3
Classifier: Operating System :: Unix
Classifier: Operating System :: MacOS :: MacOS X
Classifier: Operating System :: Microsoft :: Windows
Requires-Dist: opencv-python
